<mxGraphModel dx="800" dy="1969" grid="1" guides="1" tooltips="1" connect="1" fold="1" page="1" pageScale="1" pageWidth="826" pageHeight="1169" style="default-style2"><root><mxCell id="0"/><mxCell id="1" parent="0"/><mxCell id="58" value="" style="edgeStyle=none;endArrow=none;exitX=1;exitY=1;exitPerimeter=0;entryX=0;entryY=0.5" edge="1" parent="1" source="4" target="63"><mxGeometry width="100" height="100" relative="1" as="geometry"><mxPoint y="100" as="sourcePoint"/><mxPoint x="100" as="targetPoint"/></mxGeometry></mxCell><mxCell id="2" value="Mensa@Unibe" style="swimlane;whiteSpace=wrap" parent="1" vertex="1"><mxGeometry x="160" y="-1050" width="1320" height="2100" as="geometry"><mxRectangle x="350" y="140" width="100" height="23" as="alternateBounds"/></mxGeometry></mxCell><mxCell id="76" value="&lt;&lt;extend&gt;&gt;" style="edgeStyle=none;endArrow=classic;dashed=1;endFill=0;exitX=0.5;exitY=0;entryX=0.5;entryY=1" edge="1" parent="2" source="73" target="69"><mxGeometry x="-0.2983833718244807" y="-1.7476477097279175" width="100" height="100" relative="1" as="geometry"><mxPoint x="91.77166003959428" y="631.8202906091967" as="sourcePoint"/><mxPoint x="180" y="290" as="targetPoint"/><mxPoint x="1.1630383019697076e-12" y="3.3229665770563073e-13" as="offset"/></mxGeometry></mxCell><mxCell id="50" value="" style="edgeStyle=none;endArrow=block;dashed=1;dashPattern=1 4;entryX=0;entryY=1;exitX=0;exitY=0;endFill=0" parent="2" source="70" target="64" edge="1"><mxGeometry width="100" height="100" relative="1" as="geometry"><mxPoint x="199.99999999999943" y="229.99999999999977" as="sourcePoint"/><mxPoint x="109.99999999999989" y="89.99999999999966" as="targetPoint"/></mxGeometry></mxCell><mxCell id="49" value="" style="edgeStyle=none;endArrow=classic;dashed=1;dashPattern=1 4;entryX=0.5;entryY=1;exitX=0.5;exitY=0;endFill=0" parent="2" source="69" target="64" edge="1"><mxGeometry width="100" height="100" relative="1" as="geometry"><mxPoint x="110" y="210" as="sourcePoint"/><mxPoint x="210" y="110" as="targetPoint"/></mxGeometry></mxCell><mxCell id="10" value="" style="edgeStyle=none;endArrow=none;exitX=1;exitY=0.5" parent="2" source="65" target="67" edge="1"><mxGeometry width="100" height="100" relative="1" as="geometry"><mxPoint y="100" as="sourcePoint"/><mxPoint x="100" as="targetPoint"/></mxGeometry></mxCell><mxCell id="12" value="&lt;&lt;extend&gt;&gt;" style="edgeStyle=none;endArrow=classic;dashed=1;endFill=0" parent="2" source="68" target="66" edge="1"><mxGeometry x="0.15237250590973575" y="-6.496329826856556" width="100" height="100" relative="1" as="geometry"><mxPoint x="410" y="360" as="sourcePoint"/><mxPoint x="510" y="260" as="targetPoint"/><mxPoint x="-3.3229665770563073e-13" y="3.3229665770563073e-13" as="offset"/></mxGeometry></mxCell><mxCell id="17" value="&lt;&lt;extend&gt;&gt;" style="edgeStyle=none;endArrow=classic;dashed=1;endFill=0" parent="2" source="69" target="68" edge="1"><mxGeometry width="100" height="100" relative="1" as="geometry"><mxPoint x="355" y="240" as="sourcePoint"/><mxPoint x="205" y="230" as="targetPoint"/></mxGeometry></mxCell><mxCell id="19" value="&lt;&lt;extend&gt;&gt;" style="edgeStyle=none;endArrow=classic;dashed=1;endFill=0" parent="2" source="70" target="68" edge="1"><mxGeometry width="100" height="100" relative="1" as="geometry"><mxPoint x="290" y="330" as="sourcePoint"/><mxPoint x="440" y="290" as="targetPoint"/></mxGeometry></mxCell><mxCell id="29" value="&lt;&lt;extend&gt;&gt;" style="edgeStyle=none;endArrow=classic;dashed=1;entryX=0.5;entryY=0;endFill=0;exitX=1;exitY=1" parent="2" source="66" target="67" edge="1"><mxGeometry x="-0.14084372235852713" y="1.7036543326362503" width="100" height="100" relative="1" as="geometry"><mxPoint x="860" y="120" as="sourcePoint"/><mxPoint x="275.0000000000001" y="125.00000000000011" as="targetPoint"/><mxPoint x="-3.987559892467569e-12" y="-9.968899731168922e-13" as="offset"/></mxGeometry></mxCell><mxCell id="33" value="" style="edgeStyle=none;endArrow=none;" parent="2" source="72" target="68" edge="1"><mxGeometry width="100" height="100" relative="1" as="geometry"><mxPoint x="520" y="295.9999999999993" as="sourcePoint"/><mxPoint x="779.2" y="249.99999999999955" as="targetPoint"/></mxGeometry></mxCell><mxCell id="39" value="&lt;&lt;extend&gt;&gt;" style="edgeStyle=none;endArrow=classic;dashed=1;exitX=1;exitY=0.5;entryX=0.5;entryY=0;endFill=0" parent="2" source="71" target="72" edge="1"><mxGeometry width="100" height="100" relative="1" as="geometry"><mxPoint x="340" y="499.9999999999998" as="sourcePoint"/><mxPoint x="550" y="404.99999999999955" as="targetPoint"/></mxGeometry></mxCell><mxCell id="41" value="&lt;&lt;extend&gt;&gt;" style="edgeStyle=none;endArrow=classic;dashed=1;entryX=0.5;entryY=1;endFill=0" parent="2" source="63" target="72" edge="1"><mxGeometry width="100" height="100" relative="1" as="geometry"><mxPoint x="150" y="465" as="sourcePoint"/><mxPoint x="379.99999999999955" y="440.00000000000045" as="targetPoint"/></mxGeometry></mxCell><mxCell id="48" value="&lt;&lt;extend&gt;&gt;" style="edgeStyle=none;endArrow=classic;dashed=1;endFill=0;exitX=1;exitY=0.5" parent="2" source="64" target="66" edge="1"><mxGeometry x="-0.5307097754693011" y="1.0089498520100337" width="100" height="100" relative="1" as="geometry"><mxPoint x="250.0000000000001" y="150" as="sourcePoint"/><mxPoint x="269.9999999999999" y="89.99999999999989" as="targetPoint"/><mxPoint x="5.017679531355024e-11" y="-4.552464210567141e-11" as="offset"/></mxGeometry></mxCell><mxCell id="63" value="Nearest mensa" style="ellipse" vertex="1" parent="2"><mxGeometry x="429.99999999999994" y="690.0000000000001" width="140" height="70" as="geometry"/></mxCell><mxCell id="64" value="Favorite mensa" style="ellipse" vertex="1" parent="2"><mxGeometry x="69.99999999999997" y="49.99999999999998" width="140" height="70" as="geometry"/></mxCell><mxCell id="66" value="Detailed data" style="ellipse" vertex="1" parent="2"><mxGeometry x="930" y="880" width="140" height="70" as="geometry"/></mxCell><mxCell id="67" value="Data Source" style="ellipse" vertex="1" parent="2"><mxGeometry x="1040" y="300.0000000000001" width="140" height="70" as="geometry"/></mxCell><mxCell id="68" value="Show details of mensa" style="ellipse" vertex="1" parent="2"><mxGeometry x="689.9999999999999" y="355" width="140" height="70" as="geometry"/></mxCell><mxCell id="69" value="Show menu of day" style="ellipse" vertex="1" parent="2"><mxGeometry x="250.0000000000001" y="275" width="140" height="70" as="geometry"/></mxCell><mxCell id="70" value="Show menu of &#xa;coming day" style="ellipse" vertex="1" parent="2"><mxGeometry x="324.99999999999955" y="390.00000000000006" width="140" height="70" as="geometry"/></mxCell><mxCell id="71" value="How to reach &#xa;given mensa" style="ellipse" vertex="1" parent="2"><mxGeometry x="329.9999999999998" y="490" width="140" height="70" as="geometry"/></mxCell><mxCell id="72" value="Location of mensa" style="ellipse" vertex="1" parent="2"><mxGeometry x="449.99999999999994" y="590.0000000000001" width="140" height="70" as="geometry"/></mxCell><mxCell id="75" value="&lt;&lt;include&gt;&gt;" style="edgeStyle=none;endArrow=classic;dashed=1;endFill=0;" edge="1" parent="2" source="73" target="64"><mxGeometry x="-0.3918568301212934" y="-1.5237683036155627" width="100" height="100" relative="1" as="geometry"><mxPoint x="309.4170451467685" y="274.507600334206" as="sourcePoint"/><mxPoint x="690.580362959608" y="300.50238971287604" as="targetPoint"/><mxPoint x="-9.968899731168922e-13" y="3.3229665770563073e-13" as="offset"/></mxGeometry></mxCell><mxCell id="65" value="Show list of mensas" style="ellipse" vertex="1" parent="2"><mxGeometry x="209.99999999999994" y="159.9999999999999" width="140" height="70" as="geometry"/></mxCell><mxCell id="78" value="Notify if menu matches&#xa;some criteria in&#xa;favorite mensa" style="ellipse" vertex="1" parent="2"><mxGeometry x="334.99999999999983" y="1040" width="190.00000000000014" height="90" as="geometry"/></mxCell><mxCell id="80" value="Set criteria" style="ellipse" vertex="1" parent="2"><mxGeometry x="360.00000000000006" y="919.9999999999999" width="140" height="70" as="geometry"/></mxCell><mxCell id="82" value="&lt;&lt;include&gt;&gt;" style="edgeStyle=none;endArrow=classic;dashed=1;exitX=1;exitY=0.5;entryX=0;entryY=0.5;endFill=0" edge="1" parent="2" source="80" target="66"><mxGeometry width="100" height="100" relative="1" as="geometry"><mxPoint x="419.99999999999886" y="605" as="sourcePoint"/><mxPoint x="949.9999999999998" y="449.9999999999998" as="targetPoint"/></mxGeometry></mxCell><mxCell id="83" value="&lt;&lt;include&gt;&gt;" style="edgeStyle=none;endArrow=classic;dashed=1;endFill=0;exitX=1;exitY=0;entryX=0;entryY=0.5" edge="1" parent="2" source="78" target="66"><mxGeometry x="-0.020151655250337" y="-2.3592427189813074" width="100" height="100" relative="1" as="geometry"><mxPoint x="260.40433547335533" y="690.0751644247764" as="sourcePoint"/><mxPoint x="870" y="605.0000000000002" as="targetPoint"/><mxPoint x="6.645933154112615e-13" y="-1.6614832885281536e-13" as="offset"/></mxGeometry></mxCell><mxCell id="84" value="English translation of&#xa; a menu" style="ellipse" vertex="1" parent="2"><mxGeometry x="279.9999999999999" y="1170" width="140" height="70" as="geometry"/></mxCell><mxCell id="88" value="&lt;&lt;include&gt;&gt;" style="edgeStyle=none;endArrow=classic;dashed=1;endFill=0;exitX=1;exitY=0;entryX=0;entryY=1" edge="1" parent="2" source="84" target="66"><mxGeometry x="-0.020151655250337" y="-2.3592427189813074" width="100" height="100" relative="1" as="geometry"><mxPoint x="343.04181087376855" y="938.59608728903" as="sourcePoint"/><mxPoint x="870" y="610" as="targetPoint"/><mxPoint x="6.645933154112615e-13" y="-1.6614832885281536e-13" as="offset"/></mxGeometry></mxCell><mxCell id="73" value="Current day menu &#xa;of favorite mensa" style="ellipse" vertex="1" parent="2"><mxGeometry x="329.9999999999998" y="810.0000000000001" width="150.0000000000001" height="80" as="geometry"/></mxCell><mxCell id="91" value="&lt;&lt;extend&gt;&gt;" style="edgeStyle=none;endArrow=classic;dashed=1;endFill=0;exitX=0;exitY=0;entryX=0;entryY=1" edge="1" parent="2" source="84" target="69"><mxGeometry x="-0.2983833718244807" y="-1.7476477097279175" width="100" height="100" relative="1" as="geometry"><mxPoint x="367.49999999999955" y="819.9999999999999" as="sourcePoint"/><mxPoint x="282.4999999999998" y="354.99999999999966" as="targetPoint"/><mxPoint x="1.1630383019697076e-12" y="3.3229665770563073e-13" as="offset"/></mxGeometry></mxCell><mxCell id="92" value="Set user name" style="ellipse" vertex="1" parent="2"><mxGeometry x="280.00000000000006" y="1310" width="140" height="70" as="geometry"/></mxCell><mxCell id="93" value="Choose friends" style="ellipse" vertex="1" parent="2"><mxGeometry x="289.9999999999998" y="1450" width="140" height="70" as="geometry"/></mxCell><mxCell id="94" value="Delete a friend" style="ellipse" vertex="1" parent="2"><mxGeometry x="324.99999999999955" y="1570" width="140" height="70" as="geometry"/></mxCell><mxCell id="95" value="Enable/disable notifications&#xa;for friends" style="ellipse" vertex="1" parent="2"><mxGeometry x="300" y="1690" width="180" height="70" as="geometry"/></mxCell><mxCell id="96" value="Choose where I plan&#xa;to go for lunch" style="ellipse" vertex="1" parent="2"><mxGeometry x="320" y="1791.56992600667" width="140" height="70" as="geometry"/></mxCell><mxCell id="97" value="Get notified" style="ellipse" vertex="1" parent="2"><mxGeometry x="540" y="1786.2797040266798" width="140" height="70" as="geometry"/></mxCell><mxCell id="98" value="Rate menu" style="ellipse" vertex="1" parent="2"><mxGeometry x="279.9999999999999" y="1903.1398520133398" width="140" height="70" as="geometry"/></mxCell><mxCell id="99" value="Check rating of&#xa; a menu" style="ellipse" vertex="1" parent="2"><mxGeometry x="300.0000000000001" y="1996.6887421133895" width="140" height="70" as="geometry"/></mxCell><mxCell id="4" value="User" style="shape=umlActor;verticalLabelPosition=bottom;verticalAlign=top" parent="1" vertex="1"><mxGeometry x="39.9999999999999" y="-75" width="69.99999999999993" height="149.99999999999977" as="geometry"/></mxCell><mxCell id="5" value="Data Provider" style="ellipse;shape=cloud;whiteSpace=wrap" parent="1" vertex="1"><mxGeometry x="1500" y="-884.9999999999999" width="120" height="80" as="geometry"/></mxCell><mxCell id="6" value="" style="edgeStyle=none;endArrow=none;exitX=1;exitY=0.3333333333333333;exitPerimeter=0;entryX=0;entryY=1" parent="1" source="4" target="65" edge="1"><mxGeometry width="100" height="100" relative="1" as="geometry"><mxPoint x="-30" y="-930" as="sourcePoint"/><mxPoint x="70" y="-1030" as="targetPoint"/></mxGeometry></mxCell><mxCell id="7" value="" style="edgeStyle=none;endArrow=none;exitX=1;exitY=0.5;entryX=0.13;entryY=0.77;entryPerimeter=0" parent="1" source="67" target="5" edge="1"><mxGeometry width="100" height="100" relative="1" as="geometry"><mxPoint x="-30" y="-930" as="sourcePoint"/><mxPoint x="70" y="-1030" as="targetPoint"/></mxGeometry></mxCell><mxCell id="15" value="" style="edgeStyle=none;endArrow=none;exitX=1;exitY=0.3333333333333333;exitPerimeter=0;entryX=0;entryY=0.5" parent="1" source="4" target="69" edge="1"><mxGeometry width="100" height="100" relative="1" as="geometry"><mxPoint y="100" as="sourcePoint"/><mxPoint x="260" y="-760" as="targetPoint"/></mxGeometry></mxCell><mxCell id="25" value="" style="edgeStyle=none;endArrow=none;exitX=0;exitY=0.5;entryX=1;entryY=0.3333333333333333;entryPerimeter=0" parent="1" source="70" target="4" edge="1"><mxGeometry width="100" height="100" relative="1" as="geometry"><mxPoint y="100" as="sourcePoint"/><mxPoint x="100" as="targetPoint"/></mxGeometry></mxCell><mxCell id="31" value="GPS data" style="ellipse;shape=cloud;whiteSpace=wrap" parent="1" vertex="1"><mxGeometry x="1509.9999999999998" y="-570.0000000000001" width="120" height="80" as="geometry"/></mxCell><mxCell id="32" value="" style="edgeStyle=none;endArrow=none;exitX=1;exitY=0.5;entryX=0.16;entryY=0.55;entryPerimeter=0" parent="1" source="72" target="31" edge="1"><mxGeometry width="100" height="100" relative="1" as="geometry"><mxPoint x="770" y="-620" as="sourcePoint"/><mxPoint x="870" y="-720" as="targetPoint"/></mxGeometry></mxCell><mxCell id="43" value="" style="edgeStyle=none;endArrow=none;entryX=1;entryY=1;entryPerimeter=0;exitX=0;exitY=0.5" parent="1" source="71" target="4" edge="1"><mxGeometry width="100" height="100" relative="1" as="geometry"><mxPoint x="170" y="-630" as="sourcePoint"/><mxPoint x="270" y="-730" as="targetPoint"/></mxGeometry></mxCell><mxCell id="47" value="" style="edgeStyle=none;endArrow=none;exitX=0.75;exitY=0.1;exitPerimeter=0;entryX=0;entryY=0.5" parent="1" source="4" target="64" edge="1"><mxGeometry width="100" height="100" relative="1" as="geometry"><mxPoint x="120" y="-886.9767441860465" as="sourcePoint"/><mxPoint x="259.99999999999966" y="-913.0232558139535" as="targetPoint"/></mxGeometry></mxCell><mxCell id="74" value="" style="edgeStyle=none;endArrow=none;exitX=1;exitY=1;exitPerimeter=0;" edge="1" parent="1" source="4" target="73"><mxGeometry width="100" height="100" relative="1" as="geometry"><mxPoint y="100" as="sourcePoint"/><mxPoint x="100" as="targetPoint"/></mxGeometry></mxCell><mxCell id="79" value="" style="edgeStyle=none;endArrow=none;exitX=1;exitY=1;exitPerimeter=0;entryX=0;entryY=0.5" edge="1" parent="1" source="4" target="78"><mxGeometry width="100" height="100" relative="1" as="geometry"><mxPoint y="100" as="sourcePoint"/><mxPoint x="100" as="targetPoint"/></mxGeometry></mxCell><mxCell id="81" value="" style="edgeStyle=none;endArrow=none;exitX=1;exitY=1;exitPerimeter=0;entryX=0;entryY=0.5" edge="1" parent="1" source="4" target="80"><mxGeometry width="100" height="100" relative="1" as="geometry"><mxPoint y="100" as="sourcePoint"/><mxPoint x="100" as="targetPoint"/></mxGeometry></mxCell><mxCell id="87" value="" style="edgeStyle=none;endArrow=none;exitX=1;exitY=1;exitPerimeter=0;entryX=0;entryY=0.5" edge="1" parent="1" source="4" target="84"><mxGeometry width="100" height="100" relative="1" as="geometry"><mxPoint y="100" as="sourcePoint"/><mxPoint x="100" as="targetPoint"/></mxGeometry></mxCell><mxCell id="89" value="" style="edgeStyle=none;endArrow=none;exitX=1;exitY=0.3333333333333333;exitPerimeter=0;entryX=0;entryY=0.5" edge="1" parent="1" source="4" target="72"><mxGeometry width="100" height="100" relative="1" as="geometry"><mxPoint y="100" as="sourcePoint"/><mxPoint x="100" as="targetPoint"/></mxGeometry></mxCell><mxCell id="100" value="Friend" style="shape=umlActor;verticalLabelPosition=bottom;verticalAlign=top" vertex="1" parent="1"><mxGeometry x="1519.9999999999998" y="661.2797040266798" width="69.99999999999993" height="149.99999999999977" as="geometry"/></mxCell></root></mxGraphModel>